exportcomments/__init__.py
exportcomments/base.py
exportcomments/exceptions.py
exportcomments/export.py
exportcomments/response.py
exportcomments/settings.py
exportcomments/validation.py
exportcomments-2.0.0.dist-info/licenses/LICENSE.txt
exportcomments-2.0.0.dist-info/METADATA
exportcomments-2.0.0.dist-info/WHEEL
exportcomments-2.0.0.dist-info/top_level.txt
exportcomments-2.0.0.dist-info/RECORD
