Metadata-Version: 2.4
Name: exportcomments
Version: 2.0.0
Summary: Official Python client for the ExportComments API v3
Home-page: https://github.com/exportcomments/exportcomments-python
Download-URL: https://github.com/exportcomments/exportcomments-python/tarball/v2.0.0
Author: ExportComments
Author-email: sales@exportcomments.com
Keywords: exportcomments,export social media comments,python,api v3
Classifier: Development Status :: 5 - Production/Stable
Classifier: Programming Language :: Python :: 2
Classifier: Programming Language :: Python :: 3
Classifier: License :: OSI Approved :: MIT License
License-File: LICENSE.txt
Requires-Dist: requests>=2.8.1
Requires-Dist: six>=1.10.0
Dynamic: author
Dynamic: author-email
Dynamic: classifier
Dynamic: description
Dynamic: description-content-type
Dynamic: download-url
Dynamic: home-page
Dynamic: keywords
Dynamic: license-file
Dynamic: requires-dist
Dynamic: summary
